{
    "id": "org.webosbrew.piccap.service",
    "description" : "Picture Capture Service",
    "services" : [
        {
            "name": "org.webosbrew.piccap.service",
            "description": "Picture Capture Service",
            "commands": [
				{
                    "name": "save",
                    "description": "ele stuff",
                    "public": true
                },
                {
                    "name": "setSettings",
                    "description": "ele stuff",
                    "public": true
                },
                {
                    "name": "getSettings",
                    "description": "ele stuff",
                    "public": true
                },
                {
                    "name": "isStarted",
                    "description": "ele stuff",
                    "public": true
                },
                {
                    "name": "start",
                    "description": "ele stuff",
                    "public": true
                },
                {
                    "name": "stop",
                    "description": "ele stuff",
                    "public": true
                },
                {
                    "name": "resetSettings",
                    "description": "ele stuff",
                    "public": true
                },
                {
                    "name": "isRoot",
                    "description": "ele stuff",
                    "public": true
                },
                {
                    "name": "setCapturePerms",
                    "description": "ele stuff",
                    "public": true
                }
            ]
        }
    ],
    "version": "0.1.0"
}